{
  "Children": [
    {
      "Id": 8,
      "GlobalId": "09f519da-5d73-4bb2-88b8-d991beb18dac",
      "EntityVersionId": 13,
      "RelationName": "list of ent b",
      "OrderIndex": 3
    }
  ],
  "DisplayInMenu": true,
  "ParentPageId": -1,
  "DisplayAfter": null,
  "RecordNamePropertyId": 46,
  "UpdateRecordNameProperty": null,
  "ShowDashboardModule": false,
  "Properties": [
    {
      "Id": 46,
      "GlobalId": "029827a4-0379-4715-bd48-583c141a5417",
      "EntityVersionId": 14,
      "Name": "name",
      "Type": {
        "Id": "Text",
        "Name": "Text",
        "InputType": {
          "Id": "Text",
          "Name": "Text",
          "ValueType": 2,
          "Length": 450,
          "Icon": "short_text"
        }
      },
      "EntityVersionRefId": null,
      "IsDeleted": false,
      "IsRequired": true,
      "IsSearchable": true,
      "IsFilterable": false,
      "IsSortable": false,
      "OrderIndex": 1
    },
    {
      "Id": 47,
      "GlobalId": "ae321d31-bf29-414e-9d37-ef38aa3986a3",
      "EntityVersionId": 14,
      "Name": "ref of ent b",
      "Type": {
        "Id": "EntityRef",
        "Name": "Entity Reference",
        "InputType": {
          "Id": "EntityRef",
          "Name": "Entity Reference",
          "ValueType": 7,
          "Length": 4,
          "Icon": null
        }
      },
      "EntityVersionRefId": 13,
      "IsDeleted": false,
      "IsRequired": false,
      "IsSearchable": false,
      "IsFilterable": false,
      "IsSortable": false,
      "OrderIndex": 2
    }
  ],
  "RolePermissions": {
    "6": [
      {
        "Id": 168,
        "PermissionType": {
          "Id": 1,
          "Name": "Can View"
        },
        "RoleId": 6,
        "RoleName": "Admins",
        "Value": "all"
      },
      {
        "Id": 169,
        "PermissionType": {
          "Id": 2,
          "Name": "Can Add"
        },
        "RoleId": 6,
        "RoleName": "Admins",
        "Value": "true"
      },
      {
        "Id": 170,
        "PermissionType": {
          "Id": 3,
          "Name": "Can Edit"
        },
        "RoleId": 6,
        "RoleName": "Admins",
        "Value": "all"
      },
      {
        "Id": 171,
        "PermissionType": {
          "Id": 4,
          "Name": "Can Delete"
        },
        "RoleId": 6,
        "RoleName": "Admins",
        "Value": "all"
      }
    ],
    "7": [
      {
        "Id": 172,
        "PermissionType": {
          "Id": 1,
          "Name": "Can View"
        },
        "RoleId": 7,
        "RoleName": "Citizen Developers",
        "Value": "all"
      },
      {
        "Id": 173,
        "PermissionType": {
          "Id": 2,
          "Name": "Can Add"
        },
        "RoleId": 7,
        "RoleName": "Citizen Developers",
        "Value": "true"
      },
      {
        "Id": 174,
        "PermissionType": {
          "Id": 3,
          "Name": "Can Edit"
        },
        "RoleId": 7,
        "RoleName": "Citizen Developers",
        "Value": "all"
      },
      {
        "Id": 175,
        "PermissionType": {
          "Id": 4,
          "Name": "Can Delete"
        },
        "RoleId": 7,
        "RoleName": "Citizen Developers",
        "Value": "all"
      }
    ],
    "5": [
      {
        "Id": 176,
        "PermissionType": {
          "Id": 1,
          "Name": "Can View"
        },
        "RoleId": 5,
        "RoleName": "Low-Code Engineer",
        "Value": "all"
      },
      {
        "Id": 177,
        "PermissionType": {
          "Id": 2,
          "Name": "Can Add"
        },
        "RoleId": 5,
        "RoleName": "Low-Code Engineer",
        "Value": "true"
      },
      {
        "Id": 178,
        "PermissionType": {
          "Id": 3,
          "Name": "Can Edit"
        },
        "RoleId": 5,
        "RoleName": "Low-Code Engineer",
        "Value": "all"
      },
      {
        "Id": 179,
        "PermissionType": {
          "Id": 4,
          "Name": "Can Delete"
        },
        "RoleId": 5,
        "RoleName": "Low-Code Engineer",
        "Value": "all"
      }
    ],
    "8": [
      {
        "Id": 180,
        "PermissionType": {
          "Id": 1,
          "Name": "Can View"
        },
        "RoleId": 8,
        "RoleName": "Managers",
        "Value": "all"
      },
      {
        "Id": 181,
        "PermissionType": {
          "Id": 2,
          "Name": "Can Add"
        },
        "RoleId": 8,
        "RoleName": "Managers",
        "Value": "true"
      },
      {
        "Id": 182,
        "PermissionType": {
          "Id": 3,
          "Name": "Can Edit"
        },
        "RoleId": 8,
        "RoleName": "Managers",
        "Value": "all"
      },
      {
        "Id": 183,
        "PermissionType": {
          "Id": 4,
          "Name": "Can Delete"
        },
        "RoleId": 8,
        "RoleName": "Managers",
        "Value": "all"
      }
    ]
  },
  "Id": 14,
  "GlobalId": "ea5b252e-d0d1-4611-8252-b3bfe027d397",
  "ConfigGenerationGlobalId": "ea5b252e-d0d1-4611-8252-b3bfe027d397",
  "VersionId": 14,
  "EntityTabId": 65,
  "Name": "ent c",
  "PluralName": "ent cs",
  "PageUiLibrary": 2,
  "CreatedDate": "2022-10-24T12:22:12.9366667",
  "CreatedBy": "SuperUser Account",
  "LastModifiedBy": "",
  "LastModifiedOn": null,
  "Icon": "table",
  "Type": 0,
  "BuiltInType": null,
  "EnableIndexing": false,
  "NamespaceUid": "8098259e-211f-491a-b2c3-4f12861210ad"
}